TMC_2209/TMC_2209_StepperDriver.py
TMC_2209/_TMC_2209_GPIO_board.py
TMC_2209/_TMC_2209_comm.py
TMC_2209/_TMC_2209_logger.py
TMC_2209/_TMC_2209_math.py
TMC_2209/_TMC_2209_move.py
TMC_2209/_TMC_2209_reg.py
TMC_2209/_TMC_2209_test.py
TMC_2209/_TMC_2209_uart.py
TMC_2209/__init__.py
TMC_2209_Raspberry_Pi-0.5.6.dist-info/LICENSE
TMC_2209_Raspberry_Pi-0.5.6.dist-info/METADATA
TMC_2209_Raspberry_Pi-0.5.6.dist-info/WHEEL
TMC_2209_Raspberry_Pi-0.5.6.dist-info/top_level.txt
TMC_2209_Raspberry_Pi-0.5.6.dist-info/RECORD
