Metadata-Version: 2.1
Name: TMC_2209_Raspberry_Pi
Version: 0.5.6
Summary: this is a Python libary to drive a stepper motor with a Trinamic TMC2209 stepper driver and a Raspberry Pi
Home-page: https://github.com/Chr157i4n/TMC2209_Raspberry_Pi
Author: Christian Köhlke
Author-email: christian@koehlke.de
Project-URL: Bug Tracker, https://github.com/Chr157i4n/TMC2209_Raspberry_Pi/issues
Classifier: Programming Language :: Python :: 3
Classifier: License :: OSI Approved :: GNU General Public License v3 (GPLv3)
Classifier: Operating System :: POSIX :: Linux
Classifier: Development Status :: 4 - Beta
Classifier: Intended Audience :: Developers
Classifier: Natural Language :: English
Classifier: Topic :: System :: Hardware :: Hardware Drivers
Requires-Python: >=3.7
License-File: LICENSE
Requires-Dist: pyserial
Provides-Extra: raspberry-pi
Requires-Dist: RPi.GPIO; extra == "raspberry-pi"
Provides-Extra: raspberry-pi5
Requires-Dist: gpiozero; extra == "raspberry-pi5"
Provides-Extra: nvidia-jetson
Requires-Dist: Jetson.GPIO; extra == "nvidia-jetson"
Provides-Extra: luckfox-pico
Requires-Dist: python-periphery; extra == "luckfox-pico"
Provides-Extra: orange-pi
Requires-Dist: OPi.GPIO; extra == "orange-pi"
